{"Alphabets": ["A", "C", "E", "N", "O"], "Solutions": [{"column": 8, "id": "0e1b074aea59a0ec59aee6e9a902f6aa", "coordinates": {"CANE": ["CANE", 5, 0, "H"], "ACE": ["ACE", 5, 1, "V"], "CANOE": ["CANOE", 3, 0, "H"], "ACNE": ["ACNE", 6, 3, "H"], "EON": ["EON", 7, 1, "H"], "OCEAN": ["OCEAN", 3, 3, "V"], "CONE": ["CONE", 0, 4, "V"], "CON": ["CON", 4, 5, "V"], "ONCE": ["ONCE", 1, 4, "H"]}, "row": 8}, {"column": 8, "id": "41216bfde8d52be7a6643c04647cc04b", "coordinates": {"CANE": ["CANE", 3, 2, "V"], "ACE": ["ACE", 5, 0, "V"], "CANOE": ["CANOE", 3, 2, "H"], "ACNE": ["ACNE", 5, 0, "H"], "EON": ["EON", 5, 5, "H"], "OCEAN": ["OCEAN", 3, 5, "V"], "CONE": ["CONE", 1, 4, "H"], "ONCE": ["ONCE", 0, 6, "V"], "CON": ["CON", 1, 4, "V"]}, "row": 8}, {"column": 8, "id": "ee431292ee8032320ff20cd0cb043a66", "coordinates": {"CANE": ["CANE", 4, 1, "V"], "ACE": ["ACE", 0, 6, "V"], "CANOE": ["CANOE", 2, 3, "V"], "ACNE": ["ACNE", 3, 7, "V"], "EON": ["EON", 5, 5, "V"], "OCEAN": ["OCEAN", 5, 3, "H"], "CONE": ["CONE", 2, 3, "H"], "CON": ["CON", 4, 1, "H"], "ONCE": ["ONCE", 6, 0, "H"]}, "row": 8}, {"column": 9, "id": "e3694027971906e428078c4db381ce5c", "coordinates": {"CANE": ["CANE", 7, 3, "H"], "ACE": ["ACE", 4, 0, "H"], "CANOE": ["CANOE", 3, 2, "H"], "ACNE": ["ACNE", 0, 6, "V"], "EON": ["EON", 1, 4, "V"], "OCEAN": ["OCEAN", 3, 5, "V"], "CONE": ["CONE", 1, 1, "H"], "CON": ["CON", 1, 6, "H"], "ONCE": ["ONCE", 1, 2, "V"]}, "row": 8}, {"column": 9, "id": "b10f63c976e5fb2a77adb8e4d1e4ba6a", "coordinates": {"CANE": ["CANE", 1, 6, "V"], "ACE": ["ACE", 2, 6, "H"], "CANOE": ["CANOE", 3, 3, "V"], "ACNE": ["ACNE", 0, 4, "V"], "EON": ["EON", 4, 6, "H"], "OCEAN": ["OCEAN", 3, 2, "H"], "CONE": ["CONE", 5, 1, "H"], "ONCE": ["ONCE", 7, 0, "H"], "CON": ["CON", 5, 1, "V"]}, "row": 8}, {"column": 9, "id": "f8f1b5627fed1f40d16dd8248124bb9a", "coordinates": {"CANE": ["CANE", 6, 0, "H"], "ACE": ["ACE", 0, 6, "H"], "CANOE": ["CANOE", 4, 1, "H"], "ACNE": ["ACNE", 1, 5, "V"], "EON": ["EON", 2, 8, "V"], "OCEAN": ["OCEAN", 3, 1, "V"], "CONE": ["CONE", 2, 5, "H"], "CON": ["CON", 0, 7, "V"], "ONCE": ["ONCE", 3, 3, "V"]}, "row": 8}, {"column": 10, "id": "d747e1eef928b1aa4efc0575f8dc1930", "coordinates": {"CANE": ["CANE", 4, 2, "H"], "ACE": ["ACE", 3, 8, "V"], "CANOE": ["CANOE", 0, 5, "V"], "ACNE": ["ACNE", 1, 5, "H"], "EON": ["EON", 6, 0, "H"], "OCEAN": ["OCEAN", 3, 5, "H"], "CONE": ["CONE", 4, 2, "V"], "ONCE": ["ONCE", 0, 7, "V"], "CON": ["CON", 2, 3, "H"]}, "row": 8}, {"column": 10, "id": "e7b3eb947c6c71f23c5b079c3f8acc06", "coordinates": {"CANE": ["CANE", 4, 2, "H"], "ACE": ["ACE", 3, 8, "V"], "CANOE": ["CANOE", 0, 5, "V"], "ACNE": ["ACNE", 1, 5, "H"], "EON": ["EON", 2, 3, "H"], "OCEAN": ["OCEAN", 3, 5, "H"], "CONE": ["CONE", 4, 2, "V"], "ONCE": ["ONCE", 0, 7, "V"], "CON": ["CON", 6, 0, "H"]}, "row": 8}, {"column": 10, "id": "110a2213e34cf21dc5dc470568a4a331", "coordinates": {"CANE": ["CANE", 4, 3, "V"], "ACE": ["ACE", 1, 9, "V"], "CANOE": ["CANOE", 0, 4, "V"], "ACNE": ["ACNE", 7, 0, "H"], "EON": ["EON", 5, 6, "H"], "OCEAN": ["OCEAN", 4, 2, "H"], "CONE": ["CONE", 2, 6, "V"], "CON": ["CON", 3, 8, "V"], "ONCE": ["ONCE", 3, 6, "H"]}, "row": 8}, {"column": 10, "id": "aa5a7c1df06a4a300ab02b789b66f075", "coordinates": {"CANE": ["CANE", 4, 2, "H"], "ACE": ["ACE", 3, 8, "V"], "CANOE": ["CANOE", 0, 5, "V"], "ACNE": ["ACNE", 1, 5, "H"], "EON": ["EON", 7, 2, "H"], "OCEAN": ["OCEAN", 3, 5, "H"], "CONE": ["CONE", 4, 2, "V"], "ONCE": ["ONCE", 0, 7, "V"], "CON": ["CON", 6, 0, "H"]}, "row": 8}, {"column": 11, "id": "b5e35bf0a60456e2934a5421540a4043", "coordinates": {"CANE": ["CANE", 5, 0, "H"], "ACE": ["ACE", 6, 3, "H"], "CANOE": ["CANOE", 4, 3, "H"], "ACNE": ["ACNE", 1, 7, "V"], "EON": ["EON", 0, 9, "V"], "OCEAN": ["OCEAN", 3, 3, "V"], "CONE": ["CONE", 2, 7, "H"], "ONCE": ["ONCE", 3, 5, "V"], "CON": ["CON", 7, 1, "H"]}, "row": 8}, {"column": 11, "id": "17634ba2fd631051f564698ffc993da2", "coordinates": {"CANE": ["CANE", 3, 6, "H"], "ACE": ["ACE", 1, 8, "H"], "CANOE": ["CANOE", 4, 2, "H"], "ACNE": ["ACNE", 1, 8, "V"], "EON": ["EON", 2, 4, "H"], "OCEAN": ["OCEAN", 0, 4, "V"], "CONE": ["CONE", 4, 2, "V"], "ONCE": ["ONCE", 1, 6, "V"], "CON": ["CON", 6, 0, "H"]}, "row": 8}, {"column": 11, "id": "f0281d81b9c25e029dd9bef33e380dc3", "coordinates": {"CANE": ["CANE", 1, 7, "H"], "ACE": ["ACE", 5, 0, "V"], "CANOE": ["CANOE", 1, 7, "V"], "ACNE": ["ACNE", 0, 5, "V"], "EON": ["EON", 5, 7, "H"], "OCEAN": ["OCEAN", 3, 3, "H"], "CONE": ["CONE", 6, 0, "H"], "ONCE": ["ONCE", 3, 3, "V"], "CON": ["CON", 4, 1, "H"]}, "row": 8}, {"column": 10, "id": "bfb3e9e66ec1e6518ff2126a641cbc89", "coordinates": {"CANE": ["CANE", 5, 2, "V"], "ACE": ["ACE", 8, 0, "H"], "CANOE": ["CANOE", 2, 4, "H"], "ACNE": ["ACNE", 5, 1, "H"], "EON": ["EON", 4, 6, "H"], "OCEAN": ["OCEAN", 0, 8, "V"], "CONE": ["CONE", 2, 4, "V"], "ONCE": ["ONCE", 1, 6, "V"], "CON": ["CON", 0, 7, "H"]}, "row": 9}, {"column": 11, "id": "d4ebb037b06b9856cda885771a5335f7", "coordinates": {"CANE": ["CANE", 7, 0, "H"], "ACE": ["ACE", 1, 8, "V"], "CANOE": ["CANOE", 5, 1, "H"], "ACNE": ["ACNE", 2, 5, "V"], "EON": ["EON", 0, 10, "V"], "OCEAN": ["OCEAN", 4, 1, "V"], "CONE": ["CONE", 3, 5, "H"], "CON": ["CON", 2, 8, "H"], "ONCE": ["ONCE", 4, 3, "V"]}, "row": 9}, {"column": 10, "id": "556e55bf8fee5720aa014b9c755c61dc", "coordinates": {"CANE": ["CANE", 6, 2, "V"], "ACE": ["ACE", 7, 0, "V"], "CANOE": ["CANOE", 4, 5, "H"], "ACNE": ["ACNE", 7, 2, "H"], "EON": ["EON", 2, 7, "H"], "OCEAN": ["OCEAN", 0, 7, "V"], "CONE": ["CONE", 4, 5, "V"], "ONCE": ["ONCE", 1, 9, "V"], "CON": ["CON", 8, 0, "H"]}, "row": 10}, {"column": 12, "id": "ce98b7ac0216f8330c089b0117e407a7", "coordinates": {"CANE": ["CANE", 4, 2, "V"], "ACE": ["ACE", 7, 0, "H"], "CANOE": ["CANOE", 1, 5, "V"], "ACNE": ["ACNE", 5, 2, "H"], "EON": ["EON", 0, 10, "V"], "OCEAN": ["OCEAN", 1, 4, "H"], "CONE": ["CONE", 2, 8, "H"], "ONCE": ["ONCE", 0, 8, "V"], "CON": ["CON", 7, 1, "V"]}, "row": 10}]}