{"Alphabets": ["A", "W", "E", "R", "V", "I"], "Solutions": [{"column": 8, "id": "852dd9b70e6fdbf60daf6d7daddb75fe", "coordinates": {"VIA": ["VIA", 1, 0, "H"], "REV": ["REV", 5, 1, "V"], "WEAR": ["WEAR", 2, 7, "V"], "WAVE": ["WAVE", 0, 2, "V"], "RAW": ["RAW", 7, 5, "H"], "ARE": ["ARE", 3, 5, "H"], "WAVER": ["WAVER", 5, 3, "H"], "IRE": ["IRE", 0, 4, "V"], "VIEW": ["VIEW", 2, 2, "H"], "WAR": ["WAR", 5, 3, "V"], "WAIVER": ["WAIVER", 2, 5, "V"], "ERA": ["ERA", 6, 1, "H"]}, "row": 8}, {"column": 10, "id": "806a2bb545e9f60fa60f3324e9354745", "coordinates": {"VIA": ["VIA", 4, 6, "V"], "ERA": ["ERA", 0, 3, "V"], "WAR": ["WAR", 5, 0, "H"], "REV": ["REV", 0, 2, "H"], "WAVE": ["WAVE", 2, 2, "H"], "RAW": ["RAW", 3, 7, "H"], "ARE": ["ARE", 4, 2, "H"], "WAVER": ["WAVER", 2, 8, "V"], "VIEW": ["VIEW", 2, 4, "V"], "IRE": ["IRE", 3, 0, "H"], "WAIVER": ["WAIVER", 5, 4, "H"], "WEAR": ["WEAR", 2, 2, "V"]}, "row": 7}, {"column": 10, "id": "949691e8a9a8d401c8747872825a71e4", "coordinates": {"VIA": ["VIA", 2, 1, "V"], "WAR": ["WAR", 2, 7, "H"], "REV": ["REV", 7, 5, "H"], "WEAR": ["WEAR", 2, 7, "V"], "WAVE": ["WAVE", 4, 0, "H"], "RAW": ["RAW", 2, 9, "V"], "ERA": ["ERA", 0, 8, "V"], "WAVER": ["WAVER", 5, 3, "H"], "VIEW": ["VIEW", 2, 3, "V"], "IRE": ["IRE", 0, 6, "H"], "WAIVER": ["WAIVER", 2, 5, "V"], "ARE": ["ARE", 3, 5, "H"]}, "row": 8}, {"column": 10, "id": "a8d44dc1db77901c56b0995224e4524c", "coordinates": {"VIA": ["VIA", 5, 6, "V"], "WAR": ["WAR", 3, 6, "H"], "ARE": ["ARE", 2, 0, "H"], "REV": ["REV", 5, 4, "H"], "WAVE": ["WAVE", 4, 1, "H"], "RAW": ["RAW", 1, 0, "V"], "ERA": ["ERA", 2, 2, "V"], "WAVER": ["WAVER", 1, 4, "V"], "VIEW": ["VIEW", 0, 6, "V"], "IRE": ["IRE", 6, 6, "H"], "WAIVER": ["WAIVER", 1, 4, "H"], "WEAR": ["WEAR", 0, 8, "V"]}, "row": 8}, {"column": 10, "id": "93e43679edbd268d4195402d33c94af2", "coordinates": {"VIA": ["VIA", 0, 8, "V"], "WAR": ["WAR", 2, 7, "H"], "REV": ["REV", 2, 9, "V"], "WEAR": ["WEAR", 2, 7, "V"], "WAVE": ["WAVE", 0, 2, "V"], "RAW": ["RAW", 7, 5, "H"], "ERA": ["ERA", 1, 0, "H"], "WAVER": ["WAVER", 5, 3, "H"], "VIEW": ["VIEW", 2, 2, "H"], "IRE": ["IRE", 3, 0, "H"], "WAIVER": ["WAIVER", 2, 5, "V"], "ARE": ["ARE", 3, 5, "H"]}, "row": 8}, {"column": 10, "id": "6625d462cacf83e07bb761ced6a2e3df", "coordinates": {"VIA": ["VIA", 2, 3, "H"], "ERA": ["ERA", 4, 7, "H"], "WAR": ["WAR", 1, 5, "V"], "REV": ["REV", 3, 5, "H"], "WAVE": ["WAVE", 4, 0, "H"], "RAW": ["RAW", 3, 1, "V"], "ARE": ["ARE", 5, 4, "V"], "WAVER": ["WAVER", 5, 3, "H"], "VIEW": ["VIEW", 2, 3, "V"], "IRE": ["IRE", 7, 2, "H"], "WAIVER": ["WAIVER", 0, 7, "V"], "WEAR": ["WEAR", 1, 5, "H"]}, "row": 8}, {"column": 10, "id": "573ff6f4b84bc233db4449963eab953f", "coordinates": {"VIA": ["VIA", 4, 0, "H"], "ERA": ["ERA", 7, 1, "H"], "WAR": ["WAR", 5, 5, "V"], "REV": ["REV", 3, 9, "V"], "WAVE": ["WAVE", 0, 6, "V"], "RAW": ["RAW", 3, 7, "V"], "ARE": ["ARE", 4, 7, "H"], "WAVER": ["WAVER", 3, 2, "V"], "VIEW": ["VIEW", 5, 2, "H"], "IRE": ["IRE", 3, 4, "V"], "WAIVER": ["WAIVER", 3, 2, "H"], "WEAR": ["WEAR", 1, 4, "H"]}, "row": 8}, {"column": 10, "id": "0b453669aa420edce7da1a79ecfc33ec", "coordinates": {"VIA": ["VIA", 0, 5, "V"], "ERA": ["ERA", 6, 6, "H"], "WAR": ["WAR", 4, 7, "V"], "REV": ["REV", 0, 3, "H"], "WAVE": ["WAVE", 5, 1, "H"], "RAW": ["RAW", 7, 0, "H"], "ARE": ["ARE", 1, 9, "V"], "WAVER": ["WAVER", 2, 4, "V"], "VIEW": ["VIEW", 4, 4, "H"], "IRE": ["IRE", 2, 6, "V"], "WAIVER": ["WAIVER", 2, 4, "H"], "WEAR": ["WEAR", 5, 1, "V"]}, "row": 9}, {"column": 10, "id": "341d18729322d58d9367fff48c2a82b7", "coordinates": {"VIA": ["VIA", 5, 0, "H"], "WAR": ["WAR", 6, 5, "V"], "ARE": ["ARE", 0, 9, "V"], "REV": ["REV", 3, 0, "V"], "WAVE": ["WAVE", 4, 2, "V"], "RAW": ["RAW", 8, 5, "H"], "ERA": ["ERA", 2, 3, "V"], "WAVER": ["WAVER", 1, 6, "V"], "VIEW": ["VIEW", 6, 2, "H"], "IRE": ["IRE", 4, 4, "V"], "WAIVER": ["WAIVER", 4, 2, "H"], "WEAR": ["WEAR", 1, 6, "H"]}, "row": 9}, {"column": 11, "id": "42ad8219077bdb7dee81e55809adbe68", "coordinates": {"VIA": ["VIA", 2, 5, "H"], "ARE": ["ARE", 0, 9, "V"], "REV": ["REV", 4, 8, "V"], "WAVE": ["WAVE", 1, 7, "V"], "RAW": ["RAW", 4, 10, "V"], "ERA": ["ERA", 5, 8, "H"], "WAVER": ["WAVER", 4, 3, "V"], "IRE": ["IRE", 4, 5, "V"], "VIEW": ["VIEW", 6, 3, "H"], "WAR": ["WAR", 1, 7, "H"], "WAIVER": ["WAIVER", 4, 3, "H"], "WEAR": ["WEAR", 8, 0, "H"]}, "row": 9}, {"column": 10, "id": "5d2ebbbaf7e37c22dabfb161304fbea0", "coordinates": {"VIA": ["VIA", 0, 6, "V"], "ERA": ["ERA", 8, 0, "H"], "REV": ["REV", 2, 9, "V"], "WAVE": ["WAVE", 4, 3, "V"], "RAW": ["RAW", 4, 1, "H"], "WEAR": ["WEAR", 7, 2, "H"], "WAVER": ["WAVER", 2, 5, "H"], "IRE": ["IRE", 4, 5, "H"], "VIEW": ["VIEW", 2, 7, "V"], "WAR": ["WAR", 7, 2, "V"], "WAIVER": ["WAIVER", 2, 5, "V"], "ARE": ["ARE", 0, 8, "V"]}, "row": 10}, {"column": 10, "id": "7641d00e9694d020791e4df21e71a4ca", "coordinates": {"VIA": ["VIA", 2, 1, "H"], "WAR": ["WAR", 1, 3, "V"], "REV": ["REV", 3, 3, "H"], "WEAR": ["WEAR", 1, 3, "H"], "WAVE": ["WAVE", 4, 2, "V"], "RAW": ["RAW", 5, 7, "H"], "ARE": ["ARE", 4, 7, "V"], "WAVER": ["WAVER", 5, 1, "H"], "VIEW": ["VIEW", 7, 0, "H"], "IRE": ["IRE", 7, 1, "V"], "WAIVER": ["WAIVER", 0, 5, "V"], "ERA": ["ERA", 4, 5, "H"]}, "row": 10}, {"column": 10, "id": "0249a333c35590b5c536930088564c5e", "coordinates": {"VIA": ["VIA", 7, 5, "H"], "REV": ["REV", 3, 0, "V"], "WEAR": ["WEAR", 0, 7, "V"], "WAVE": ["WAVE", 5, 5, "V"], "RAW": ["RAW", 8, 7, "H"], "ERA": ["ERA", 4, 0, "H"], "WAVER": ["WAVER", 3, 2, "V"], "IRE": ["IRE", 3, 4, "V"], "VIEW": ["VIEW", 5, 2, "H"], "WAR": ["WAR", 7, 0, "H"], "WAIVER": ["WAIVER", 3, 2, "H"], "ARE": ["ARE", 7, 7, "V"]}, "row": 10}, {"column": 12, "id": "eb982382d4cca67d53d61bddce14afd8", "coordinates": {"VIA": ["VIA", 0, 8, "V"], "REV": ["REV", 7, 0, "H"], "WEAR": ["WEAR", 2, 7, "V"], "WAVE": ["WAVE", 5, 2, "V"], "RAW": ["RAW", 5, 9, "H"], "ARE": ["ARE", 4, 7, "H"], "WAVER": ["WAVER", 3, 5, "V"], "IRE": ["IRE", 6, 0, "V"], "VIEW": ["VIEW", 3, 2, "H"], "WAR": ["WAR", 2, 7, "H"], "WAIVER": ["WAIVER", 5, 2, "H"], "ERA": ["ERA", 4, 9, "V"]}, "row": 9}, {"column": 12, "id": "e2505c4fb9fae7fb0c79b2410ee0615d", "coordinates": {"VIA": ["VIA", 0, 9, "V"], "ERA": ["ERA", 2, 7, "H"], "REV": ["REV", 7, 1, "V"], "WAVE": ["WAVE", 1, 5, "V"], "RAW": ["RAW", 4, 6, "V"], "WEAR": ["WEAR", 8, 0, "H"], "WAVER": ["WAVER", 4, 2, "H"], "IRE": ["IRE", 1, 9, "H"], "VIEW": ["VIEW", 6, 3, "H"], "WAR": ["WAR", 1, 5, "H"], "WAIVER": ["WAIVER", 3, 3, "V"], "ARE": ["ARE", 0, 7, "V"]}, "row": 10}]}