{"Alphabets": ["E", "D", "N", "D", "O", "W"], "Solutions": [{"column": 9, "id": "d54453cc862960e28b4baedb3b2aa500", "coordinates": {"NODE": ["NODE", 1, 2, "V"], "OWN": ["OWN", 3, 7, "V"], "DON": ["DON", 0, 4, "H"], "OWE": ["OWE", 1, 6, "H"], "DOWNED": ["DOWNED", 2, 1, "H"], "EON": ["EON", 2, 5, "V"], "ONE": ["ONE", 4, 0, "H"], "NOD": ["NOD", 0, 6, "V"], "DEN": ["DEN", 0, 4, "V"], "WOE": ["WOE", 3, 0, "V"], "NEW": ["NEW", 4, 5, "H"], "DEW": ["DEW", 0, 8, "V"]}, "row": 6}, {"column": 8, "id": "e708dbcc4911a81111ab71b0945170a5", "coordinates": {"NODE": ["NODE", 3, 4, "H"], "OWN": ["OWN", 3, 0, "V"], "DON": ["DON", 3, 6, "V"], "NOD": ["NOD", 0, 2, "V"], "DOWNED": ["DOWNED", 0, 4, "V"], "EON": ["EON", 0, 0, "H"], "ONE": ["ONE", 4, 2, "H"], "OWE": ["OWE", 4, 2, "V"], "DEN": ["DEN", 5, 4, "H"], "WOE": ["WOE", 1, 7, "V"], "NEW": ["NEW", 5, 0, "H"], "DEW": ["DEW", 2, 2, "H"]}, "row": 7}, {"column": 9, "id": "b1ec0322c21d5f7a32f2bb9ea4cb41c8", "coordinates": {"NODE": ["NODE", 1, 2, "V"], "OWN": ["OWN", 3, 6, "H"], "DON": ["DON", 2, 6, "V"], "NOD": ["NOD", 2, 4, "V"], "DOWNED": ["DOWNED", 2, 1, "H"], "EON": ["EON", 4, 5, "V"], "ONE": ["ONE", 4, 1, "V"], "OWE": ["OWE", 0, 5, "V"], "DEN": ["DEN", 4, 4, "H"], "WOE": ["WOE", 4, 0, "H"], "NEW": ["NEW", 3, 8, "V"], "DEW": ["DEW", 6, 0, "H"]}, "row": 7}, {"column": 9, "id": "90030c73fe55bdff467e1d2b897a1123", "coordinates": {"NODE": ["NODE", 2, 6, "V"], "OWN": ["OWN", 4, 2, "V"], "DON": ["DON", 0, 3, "H"], "OWE": ["OWE", 3, 6, "H"], "DOWNED": ["DOWNED", 4, 1, "H"], "EON": ["EON", 5, 6, "H"], "DEW": ["DEW", 0, 3, "V"], "NOD": ["NOD", 2, 1, "V"], "DEN": ["DEN", 6, 0, "H"], "WOE": ["WOE", 1, 8, "V"], "NEW": ["NEW", 2, 1, "H"], "ONE": ["ONE", 3, 4, "V"]}, "row": 7}, {"column": 9, "id": "ba4b5b6fe5caa432dee88b7403addadf", "coordinates": {"NODE": ["NODE", 2, 3, "V"], "OWN": ["OWN", 5, 6, "H"], "DON": ["DON", 4, 3, "H"], "NOD": ["NOD", 0, 0, "H"], "DOWNED": ["DOWNED", 2, 0, "H"], "EON": ["EON", 3, 5, "H"], "DEW": ["DEW", 0, 2, "V"], "OWE": ["OWE", 4, 1, "V"], "DEN": ["DEN", 2, 5, "V"], "WOE": ["WOE", 5, 1, "H"], "NEW": ["NEW", 3, 7, "V"], "ONE": ["ONE", 0, 4, "V"]}, "row": 7}, {"column": 8, "id": "43cfcfecace9b5ccfa612c4925787721", "coordinates": {"NODE": ["NODE", 3, 1, "V"], "OWN": ["OWN", 5, 6, "V"], "DON": ["DON", 2, 3, "V"], "OWE": ["OWE", 0, 3, "H"], "DOWNED": ["DOWNED", 4, 0, "H"], "EON": ["EON", 4, 4, "V"], "DEW": ["DEW", 6, 0, "H"], "NOD": ["NOD", 2, 5, "V"], "DEN": ["DEN", 2, 3, "H"], "WOE": ["WOE", 0, 4, "V"], "NEW": ["NEW", 6, 4, "H"], "ONE": ["ONE", 3, 5, "H"]}, "row": 8}, {"column": 8, "id": "a58b9441186f36b7f2a14c4803927978", "coordinates": {"NODE": ["NODE", 3, 4, "H"], "OWN": ["OWN", 5, 5, "V"], "DON": ["DON", 5, 4, "H"], "NOD": ["NOD", 7, 5, "H"], "DOWNED": ["DOWNED", 0, 4, "V"], "EON": ["EON", 0, 2, "V"], "ONE": ["ONE", 4, 2, "H"], "OWE": ["OWE", 1, 7, "V"], "DEN": ["DEN", 3, 6, "V"], "WOE": ["WOE", 0, 0, "H"], "NEW": ["NEW", 2, 2, "H"], "DEW": ["DEW", 0, 4, "H"]}, "row": 8}, {"column": 8, "id": "e6678acfa25bca5fdb808f2dffb61888", "coordinates": {"NODE": ["NODE", 4, 4, "V"], "OWN": ["OWN", 4, 2, "V"], "DON": ["DON", 6, 4, "H"], "NOD": ["NOD", 2, 1, "V"], "DOWNED": ["DOWNED", 4, 1, "H"], "EON": ["EON", 6, 0, "H"], "DEW": ["DEW", 5, 0, "V"], "OWE": ["OWE", 2, 5, "V"], "DEN": ["DEN", 4, 6, "V"], "WOE": ["WOE", 0, 7, "V"], "NEW": ["NEW", 2, 3, "V"], "ONE": ["ONE", 2, 5, "H"]}, "row": 8}, {"column": 8, "id": "6ba0aacfc6fb3bbacae4e3c52db78e68", "coordinates": {"NODE": ["NODE", 5, 0, "H"], "OWN": ["OWN", 5, 5, "H"], "DON": ["DON", 4, 5, "V"], "NOD": ["NOD", 4, 3, "H"], "DOWNED": ["DOWNED", 1, 3, "V"], "EON": ["EON", 4, 1, "V"], "ONE": ["ONE", 2, 3, "H"], "OWE": ["OWE", 0, 5, "V"], "DEN": ["DEN", 6, 3, "H"], "WOE": ["WOE", 1, 5, "H"], "NEW": ["NEW", 5, 7, "V"], "DEW": ["DEW", 0, 7, "V"]}, "row": 8}, {"column": 9, "id": "809ffe0b2a80bf08b531fe457c6cf667", "coordinates": {"NODE": ["NODE", 2, 4, "H"], "OWN": ["OWN", 4, 1, "V"], "DON": ["DON", 2, 2, "V"], "OWE": ["OWE", 0, 6, "H"], "DOWNED": ["DOWNED", 2, 6, "V"], "EON": ["EON", 4, 0, "H"], "DEW": ["DEW", 6, 5, "H"], "NOD": ["NOD", 2, 0, "H"], "DEN": ["DEN", 0, 0, "V"], "WOE": ["WOE", 0, 7, "V"], "NEW": ["NEW", 2, 4, "V"], "ONE": ["ONE", 3, 2, "H"]}, "row": 8}, {"column": 10, "id": "e779354e486a97d3fb20ce4320d3b422", "coordinates": {"NODE": ["NODE", 3, 3, "V"], "OWN": ["OWN", 3, 1, "V"], "DON": ["DON", 3, 5, "V"], "NOD": ["NOD", 5, 1, "H"], "DOWNED": ["DOWNED", 3, 0, "H"], "EON": ["EON", 7, 7, "H"], "ONE": ["ONE", 1, 4, "H"], "OWE": ["OWE", 1, 4, "V"], "DEN": ["DEN", 5, 9, "V"], "WOE": ["WOE", 5, 7, "V"], "NEW": ["NEW", 5, 5, "H"], "DEW": ["DEW", 0, 6, "V"]}, "row": 8}, {"column": 9, "id": "12dd681c89ced72690737e0c61bd3487", "coordinates": {"NODE": ["NODE", 2, 5, "V"], "OWN": ["OWN", 6, 6, "H"], "DON": ["DON", 0, 5, "H"], "OWE": ["OWE", 7, 4, "H"], "DOWNED": ["DOWNED", 2, 2, "H"], "EON": ["EON", 4, 0, "H"], "ONE": ["ONE", 0, 6, "V"], "NOD": ["NOD", 6, 8, "V"], "DEN": ["DEN", 2, 2, "V"], "WOE": ["WOE", 5, 6, "V"], "NEW": ["NEW", 5, 4, "H"], "DEW": ["DEW", 2, 7, "V"]}, "row": 9}, {"column": 9, "id": "ec3afb2460b5eedd1cdeeb14ed65422d", "coordinates": {"NODE": ["NODE", 2, 5, "V"], "OWN": ["OWN", 5, 2, "V"], "DON": ["DON", 5, 6, "V"], "NOD": ["NOD", 5, 4, "V"], "DOWNED": ["DOWNED", 5, 1, "H"], "EON": ["EON", 7, 0, "H"], "ONE": ["ONE", 6, 6, "H"], "OWE": ["OWE", 4, 8, "V"], "DEN": ["DEN", 7, 4, "H"], "WOE": ["WOE", 0, 6, "V"], "NEW": ["NEW", 2, 5, "H"], "DEW": ["DEW", 6, 0, "V"]}, "row": 9}, {"column": 9, "id": "1ee1710e5455dd588d4c547657d59d5a", "coordinates": {"NODE": ["NODE", 1, 6, "V"], "OWN": ["OWN", 5, 0, "H"], "DON": ["DON", 1, 4, "H"], "OWE": ["OWE", 2, 6, "H"], "DOWNED": ["DOWNED", 3, 1, "H"], "EON": ["EON", 6, 2, "H"], "ONE": ["ONE", 7, 4, "H"], "NOD": ["NOD", 6, 4, "V"], "DEN": ["DEN", 1, 4, "V"], "WOE": ["WOE", 0, 8, "V"], "NEW": ["NEW", 5, 2, "V"], "DEW": ["DEW", 3, 1, "V"]}, "row": 9}, {"column": 9, "id": "fcff5938d677a7638107387cb3c1ac50", "coordinates": {"NODE": ["NODE", 1, 2, "V"], "OWN": ["OWN", 4, 0, "V"], "DON": ["DON", 0, 4, "H"], "OWE": ["OWE", 1, 6, "H"], "DOWNED": ["DOWNED", 2, 1, "H"], "EON": ["EON", 2, 5, "V"], "ONE": ["ONE", 4, 0, "H"], "NOD": ["NOD", 0, 6, "V"], "DEN": ["DEN", 0, 4, "V"], "WOE": ["WOE", 6, 2, "V"], "NEW": ["NEW", 6, 0, "H"], "DEW": ["DEW", 0, 8, "V"]}, "row": 9}, {"column": 11, "id": "ec53316ff7c7565757117e977b9588eb", "coordinates": {"NODE": ["NODE", 2, 4, "V"], "OWN": ["OWN", 0, 8, "V"], "DON": ["DON", 2, 6, "H"], "OWE": ["OWE", 5, 2, "H"], "DOWNED": ["DOWNED", 4, 4, "H"], "EON": ["EON", 4, 8, "V"], "ONE": ["ONE", 5, 2, "V"], "NOD": ["NOD", 0, 2, "V"], "DEN": ["DEN", 2, 2, "H"], "WOE": ["WOE", 7, 0, "H"], "NEW": ["NEW", 6, 8, "H"], "DEW": ["DEW", 2, 6, "V"]}, "row": 8}, {"column": 10, "id": "69e93d106fcb604ca8936c2f85c06130", "coordinates": {"NODE": ["NODE", 2, 4, "V"], "OWN": ["OWN", 4, 0, "H"], "DON": ["DON", 0, 1, "H"], "NOD": ["NOD", 4, 6, "H"], "DOWNED": ["DOWNED", 2, 1, "H"], "EON": ["EON", 6, 7, "H"], "DEW": ["DEW", 2, 1, "V"], "OWE": ["OWE", 6, 8, "V"], "DEN": ["DEN", 2, 6, "V"], "WOE": ["WOE", 0, 5, "V"], "NEW": ["NEW", 0, 3, "V"], "ONE": ["ONE", 4, 7, "V"]}, "row": 9}, {"column": 10, "id": "35e4a7dc654ab6802fb1265eccd839fd", "coordinates": {"NODE": ["NODE", 2, 4, "V"], "OWN": ["OWN", 5, 2, "V"], "DON": ["DON", 6, 7, "H"], "NOD": ["NOD", 4, 7, "V"], "DOWNED": ["DOWNED", 4, 4, "H"], "EON": ["EON", 2, 2, "H"], "ONE": ["ONE", 5, 2, "H"], "OWE": ["OWE", 6, 8, "V"], "DEN": ["DEN", 4, 9, "V"], "WOE": ["WOE", 0, 2, "V"], "NEW": ["NEW", 2, 6, "V"], "DEW": ["DEW", 0, 0, "H"]}, "row": 9}, {"column": 10, "id": "03a6e7f0aa36163eef1fab9b77156605", "coordinates": {"NODE": ["NODE", 5, 0, "H"], "OWN": ["OWN", 6, 5, "H"], "DON": ["DON", 3, 0, "H"], "OWE": ["OWE", 6, 5, "V"], "DOWNED": ["DOWNED", 0, 2, "V"], "EON": ["EON", 5, 3, "V"], "DEW": ["DEW", 8, 7, "H"], "NOD": ["NOD", 6, 7, "V"], "DEN": ["DEN", 3, 0, "V"], "WOE": ["WOE", 1, 1, "H"], "NEW": ["NEW", 7, 3, "H"], "ONE": ["ONE", 5, 1, "V"]}, "row": 9}]}