{"Alphabets": ["T", "E", "M", "E", "O", "D"], "Solutions": [{"column": 10, "id": "01998d5c75fc2f39ccb8b3f5091cdfdf", "coordinates": {"DEMO": ["DEMO", 2, 1, "V"], "TEE": ["TEE", 6, 5, "H"], "DOME": ["DOME", 4, 3, "H"], "MET": ["MET", 4, 5, "V"], "DEEM": ["DEEM", 0, 8, "V"], "MODE": ["MODE", 2, 3, "V"], "METE": ["METE", 1, 6, "V"], "MEET": ["MEET", 1, 6, "H"], "DEMOTE": ["DEMOTE", 2, 1, "H"], "TOME": ["TOME", 3, 6, "H"], "DOT": ["DOT", 0, 0, "H"], "TOE": ["TOE", 0, 2, "V"]}, "row": 7}, {"column": 9, "id": "e28c8e62ab51e7fadb661439911e0f13", "coordinates": {"DEMO": ["DEMO", 3, 0, "H"], "TEE": ["TEE", 7, 0, "H"], "DOME": ["DOME", 1, 0, "H"], "MET": ["MET", 4, 6, "H"], "DEEM": ["DEEM", 1, 6, "V"], "MODE": ["MODE", 0, 1, "V"], "METE": ["METE", 2, 3, "H"], "MEET": ["MEET", 5, 2, "V"], "DEMOTE": ["DEMOTE", 0, 3, "V"], "TOME": ["TOME", 5, 0, "H"], "DOT": ["DOT", 3, 0, "V"], "TOE": ["TOE", 8, 2, "H"]}, "row": 9}, {"column": 9, "id": "85276a169800c04ab07c52ba85011b43", "coordinates": {"DEMO": ["DEMO", 0, 4, "V"], "TEE": ["TEE", 4, 6, "H"], "DOME": ["DOME", 7, 0, "H"], "MET": ["MET", 2, 6, "H"], "DEEM": ["DEEM", 5, 5, "V"], "MODE": ["MODE", 5, 3, "H"], "METE": ["METE", 1, 3, "H"], "MEET": ["MEET", 5, 3, "V"], "DEMOTE": ["DEMOTE", 0, 6, "V"], "TOME": ["TOME", 8, 3, "H"], "DOT": ["DOT", 6, 1, "V"], "TOE": ["TOE", 2, 8, "V"]}, "row": 9}, {"column": 11, "id": "f2123586693e080589adb8828e6be3e0", "coordinates": {"DEMO": ["DEMO", 4, 0, "H"], "DOME": ["DOME", 1, 2, "H"], "TEE": ["TEE", 2, 10, "V"], "MET": ["MET", 5, 4, "V"], "DEEM": ["DEEM", 1, 2, "V"], "MODE": ["MODE", 3, 4, "H"], "METE": ["METE", 5, 4, "H"], "MEET": ["MEET", 2, 7, "H"], "DEMOTE": ["DEMOTE", 0, 5, "V"], "TOME": ["TOME", 0, 7, "V"], "DOT": ["DOT", 0, 5, "H"], "TOE": ["TOE", 5, 6, "V"]}, "row": 8}, {"column": 11, "id": "a257fadf23e9598afeff8f6e462119ea", "coordinates": {"DEMO": ["DEMO", 1, 0, "H"], "DOME": ["DOME", 2, 4, "V"], "TEE": ["TEE", 0, 10, "V"], "MET": ["MET", 0, 8, "H"], "DEEM": ["DEEM", 5, 3, "H"], "MODE": ["MODE", 0, 6, "V"], "METE": ["METE", 0, 8, "V"], "MEET": ["MEET", 1, 2, "V"], "DEMOTE": ["DEMOTE", 3, 1, "H"], "TOME": ["TOME", 1, 5, "H"], "DOT": ["DOT", 5, 3, "V"], "TOE": ["TOE", 2, 8, "H"]}, "row": 8}, {"column": 10, "id": "11ad848d5c8fd137ef0e304cfbc153fd", "coordinates": {"DEMO": ["DEMO", 2, 5, "V"], "TEE": ["TEE", 7, 4, "H"], "DOME": ["DOME", 2, 5, "H"], "MET": ["MET", 6, 0, "H"], "DEEM": ["DEEM", 5, 6, "V"], "MODE": ["MODE", 5, 4, "H"], "METE": ["METE", 5, 4, "V"], "MEET": ["MEET", 5, 1, "V"], "DEMOTE": ["DEMOTE", 0, 7, "V"], "TOME": ["TOME", 8, 1, "H"], "DOT": ["DOT", 0, 7, "H"], "TOE": ["TOE", 4, 7, "H"]}, "row": 9}, {"column": 10, "id": "0c0e7bccf59409727dcfe2ea131f0861", "coordinates": {"DEMO": ["DEMO", 1, 1, "H"], "DOME": ["DOME", 3, 1, "H"], "TEE": ["TEE", 2, 9, "V"], "MET": ["MET", 8, 2, "H"], "DEEM": ["DEEM", 5, 0, "H"], "MODE": ["MODE", 5, 3, "V"], "METE": ["METE", 2, 4, "H"], "MEET": ["MEET", 0, 7, "V"], "DEMOTE": ["DEMOTE", 0, 2, "V"], "TOME": ["TOME", 0, 4, "V"], "DOT": ["DOT", 5, 0, "V"], "TOE": ["TOE", 3, 7, "H"]}, "row": 9}, {"column": 10, "id": "3eba927f8f4ac49d73eafd5cc1025501", "coordinates": {"DEMO": ["DEMO", 1, 1, "V"], "DOME": ["DOME", 1, 3, "V"], "TEE": ["TEE", 3, 8, "V"], "MET": ["MET", 5, 7, "H"], "DEEM": ["DEEM", 0, 5, "V"], "MODE": ["MODE", 4, 0, "H"], "METE": ["METE", 4, 0, "V"], "MEET": ["MEET", 3, 5, "H"], "DEMOTE": ["DEMOTE", 2, 0, "H"], "TOME": ["TOME", 5, 9, "V"], "DOT": ["DOT", 4, 2, "V"], "TOE": ["TOE", 1, 7, "V"]}, "row": 9}, {"column": 12, "id": "97d6a81911c8379b50de1b54081629f4", "coordinates": {"DEMO": ["DEMO", 1, 5, "H"], "TEE": ["TEE", 4, 4, "V"], "DOME": ["DOME", 1, 5, "V"], "MET": ["MET", 5, 6, "H"], "DEEM": ["DEEM", 3, 1, "V"], "MODE": ["MODE", 6, 1, "H"], "METE": ["METE", 3, 5, "H"], "MEET": ["MEET", 2, 8, "H"], "DEMOTE": ["DEMOTE", 4, 0, "H"], "TOME": ["TOME", 0, 8, "V"], "DOT": ["DOT", 6, 3, "V"], "TOE": ["TOE", 3, 7, "V"]}, "row": 9}, {"column": 11, "id": "186eb7962a1a6516ea513ffed755aef3", "coordinates": {"DEMO": ["DEMO", 3, 2, "V"], "TEE": ["TEE", 5, 0, "V"], "DOME": ["DOME", 0, 3, "V"], "MET": ["MET", 4, 8, "H"], "DEEM": ["DEEM", 3, 2, "H"], "MODE": ["MODE", 3, 5, "V"], "METE": ["METE", 4, 8, "V"], "MEET": ["MEET", 6, 6, "V"], "DEMOTE": ["DEMOTE", 6, 4, "H"], "TOME": ["TOME", 5, 0, "H"], "DOT": ["DOT", 6, 4, "V"], "TOE": ["TOE", 8, 4, "H"]}, "row": 10}, {"column": 11, "id": "34dfef778b6f4ab068513d438526b169", "coordinates": {"DEMO": ["DEMO", 6, 2, "V"], "TEE": ["TEE", 7, 0, "H"], "DOME": ["DOME", 3, 3, "V"], "MET": ["MET", 6, 4, "V"], "DEEM": ["DEEM", 3, 3, "H"], "MODE": ["MODE", 0, 5, "V"], "METE": ["METE", 5, 7, "V"], "MEET": ["MEET", 5, 7, "H"], "DEMOTE": ["DEMOTE", 6, 2, "H"], "TOME": ["TOME", 8, 4, "H"], "DOT": ["DOT", 3, 10, "V"], "TOE": ["TOE", 3, 8, "V"]}, "row": 10}]}