{"Alphabets": ["I", "L", "R", "L", "D"], "Solutions": [{"column": 6, "id": "c76a66f1ffa4a3d0630307ede4fcf29b", "coordinates": {"LID": ["LID", 0, 0, "V"], "RID": ["RID", 0, 3, "H"], "ILL": ["ILL", 0, 4, "V"], "DRILL": ["DRILL", 2, 0, "H"]}, "row": 3}, {"column": 5, "id": "0e17c5a6872a6677ef055c6d5fd8a94f", "coordinates": {"LID": ["LID", 1, 2, "V"], "RID": ["RID", 0, 0, "V"], "ILL": ["ILL", 0, 4, "V"], "DRILL": ["DRILL", 2, 0, "H"]}, "row": 4}, {"column": 5, "id": "6c117efbf26bfd30e10b9676808db104", "coordinates": {"LID": ["LID", 0, 0, "V"], "RID": ["RID", 1, 2, "V"], "ILL": ["ILL", 1, 4, "V"], "DRILL": ["DRILL", 2, 0, "H"]}, "row": 4}, {"column": 6, "id": "1ca0aeacd1811e7508cd856f57ef8df5", "coordinates": {"LID": ["LID", 3, 0, "H"], "RID": ["RID", 1, 2, "V"], "ILL": ["ILL", 0, 4, "V"], "DRILL": ["DRILL", 1, 1, "H"]}, "row": 4}, {"column": 6, "id": "4905c8f1bfe5c201871eb35566e6c9fb", "coordinates": {"LID": ["LID", 0, 3, "H"], "RID": ["RID", 1, 2, "V"], "ILL": ["ILL", 0, 4, "V"], "DRILL": ["DRILL", 2, 0, "H"]}, "row": 4}, {"column": 5, "id": "7845033de512beaf408157050388d3bf", "coordinates": {"LID": ["LID", 0, 0, "V"], "RID": ["RID", 2, 1, "V"], "ILL": ["ILL", 0, 4, "V"], "DRILL": ["DRILL", 2, 0, "H"]}, "row": 5}, {"column": 5, "id": "e8b3df7cd153618d713cab547863f802", "coordinates": {"LID": ["LID", 3, 2, "H"], "RID": ["RID", 1, 2, "H"], "ILL": ["ILL", 4, 0, "H"], "DRILL": ["DRILL", 0, 2, "V"]}, "row": 5}, {"column": 5, "id": "185fa433b79b72a3b5dc01fcf9cae0d9", "coordinates": {"LID": ["LID", 2, 4, "V"], "RID": ["RID", 0, 0, "V"], "ILL": ["ILL", 2, 2, "V"], "DRILL": ["DRILL", 2, 0, "H"]}, "row": 5}, {"column": 5, "id": "0e68f1c8e2168e690347f22509dee14f", "coordinates": {"LID": ["LID", 0, 0, "V"], "RID": ["RID", 2, 1, "V"], "ILL": ["ILL", 1, 4, "V"], "DRILL": ["DRILL", 2, 0, "H"]}, "row": 5}, {"column": 5, "id": "089c6e73bd4910e66e70446856a30472", "coordinates": {"LID": ["LID", 4, 2, "H"], "RID": ["RID", 1, 2, "H"], "ILL": ["ILL", 3, 0, "H"], "DRILL": ["DRILL", 0, 2, "V"]}, "row": 5}, {"column": 5, "id": "ebcbe1da860508d5e983bd7929869f3c", "coordinates": {"LID": ["LID", 4, 2, "H"], "RID": ["RID", 0, 0, "H"], "ILL": ["ILL", 2, 2, "H"], "DRILL": ["DRILL", 0, 2, "V"]}, "row": 5}, {"column": 5, "id": "f72ab82d8f4d633658e89a0a673b89c0", "coordinates": {"LID": ["LID", 0, 0, "V"], "RID": ["RID", 2, 1, "V"], "ILL": ["ILL", 0, 3, "V"], "DRILL": ["DRILL", 2, 0, "H"]}, "row": 5}, {"column": 7, "id": "d368475ca8e6c5b9f53e21da3e210433", "coordinates": {"LID": ["LID", 1, 4, "V"], "ILL": ["ILL", 2, 4, "H"], "RID": ["RID", 0, 2, "V"], "DRILL": ["DRILL", 1, 0, "H"]}, "row": 4}]}