{"Alphabets": ["G", "U", "S", "T", "E"], "Solutions": [{"column": 8, "id": "e45d144ca69329e2379c8ada4b192707", "coordinates": {"SUE": ["SUE", 2, 0, "H"], "SET": ["SET", 3, 2, "H"], "GUEST": ["GUEST", 0, 2, "V"], "GET": ["GET", 4, 0, "H"], "GUST": ["GUST", 0, 2, "H"], "USE": ["USE", 2, 6, "V"], "GUT": ["GUT", 2, 5, "H"], "TUG": ["TUG", 0, 5, "V"]}, "row": 5}, {"column": 8, "id": "123f27aa12b9bc0f65c83e793cd06230", "coordinates": {"USE": ["USE", 1, 5, "H"], "SET": ["SET", 0, 7, "V"], "GUEST": ["GUEST", 2, 1, "H"], "GET": ["GET", 4, 0, "H"], "GUST": ["GUST", 1, 2, "V"], "SUE": ["SUE", 2, 4, "V"], "GUT": ["GUT", 0, 5, "V"], "TUG": ["TUG", 0, 3, "H"]}, "row": 5}, {"column": 8, "id": "9aee2eb14574bbd5d0adcdef42d2aff2", "coordinates": {"USE": ["USE", 4, 0, "H"], "SET": ["SET", 5, 4, "H"], "GUEST": ["GUEST", 3, 2, "H"], "GET": ["GET", 3, 2, "V"], "GUST": ["GUST", 0, 6, "V"], "SUE": ["SUE", 3, 5, "V"], "GUT": ["GUT", 3, 0, "V"], "TUG": ["TUG", 1, 5, "H"]}, "row": 6}, {"column": 8, "id": "fafb68c54108a12a43163a670cf3531f", "coordinates": {"USE": ["USE", 4, 0, "H"], "SET": ["SET", 2, 4, "V"], "GUEST": ["GUEST", 2, 1, "H"], "GET": ["GET", 0, 5, "H"], "GUST": ["GUST", 2, 1, "V"], "SUE": ["SUE", 0, 3, "V"], "GUT": ["GUT", 0, 5, "V"], "TUG": ["TUG", 0, 7, "V"]}, "row": 6}, {"column": 7, "id": "cdab3c7cf9da70d39f6ce2775e995ba4", "coordinates": {"SUE": ["SUE", 6, 2, "H"], "SET": ["SET", 2, 3, "V"], "GUEST": ["GUEST", 2, 0, "H"], "GET": ["GET", 0, 4, "H"], "GUST": ["GUST", 1, 1, "V"], "USE": ["USE", 4, 4, "V"], "GUT": ["GUT", 0, 4, "V"], "TUG": ["TUG", 4, 3, "H"]}, "row": 7}, {"column": 9, "id": "8569ab1a6d9d7cbb0761511bd143d64a", "coordinates": {"SUE": ["SUE", 4, 0, "H"], "SET": ["SET", 2, 6, "H"], "GUEST": ["GUEST", 3, 2, "H"], "GET": ["GET", 3, 2, "V"], "GUST": ["GUST", 0, 6, "V"], "USE": ["USE", 1, 4, "V"], "GUT": ["GUT", 0, 6, "H"], "TUG": ["TUG", 5, 2, "H"]}, "row": 6}, {"column": 9, "id": "4e65aae1d3385ffe8a54f2e8f1ad1037", "coordinates": {"USE": ["USE", 1, 6, "H"], "SET": ["SET", 3, 0, "H"], "GUEST": ["GUEST", 1, 4, "V"], "GET": ["GET", 5, 2, "H"], "GUST": ["GUST", 2, 3, "H"], "SUE": ["SUE", 4, 4, "H"], "GUT": ["GUT", 0, 6, "V"], "TUG": ["TUG", 3, 2, "V"]}, "row": 6}, {"column": 9, "id": "dc77df178fda975c70ffda5d4a870b8b", "coordinates": {"SUE": ["SUE", 0, 6, "H"], "SET": ["SET", 0, 6, "V"], "GUEST": ["GUEST", 2, 0, "H"], "GET": ["GET", 1, 2, "V"], "GUST": ["GUST", 2, 0, "V"], "USE": ["USE", 1, 4, "H"], "GUT": ["GUT", 0, 4, "V"], "TUG": ["TUG", 5, 0, "H"]}, "row": 6}, {"column": 8, "id": "4d8be8cd6b8e73d56a4e726addd0f6dc", "coordinates": {"USE": ["USE", 3, 5, "H"], "SET": ["SET", 0, 3, "V"], "GUEST": ["GUEST", 4, 1, "H"], "GET": ["GET", 6, 0, "H"], "GUST": ["GUST", 3, 2, "V"], "SUE": ["SUE", 1, 7, "V"], "GUT": ["GUT", 2, 5, "V"], "TUG": ["TUG", 2, 3, "H"]}, "row": 7}, {"column": 8, "id": "25dc580f958b6129389e2936d071db3a", "coordinates": {"USE": ["USE", 1, 5, "H"], "SET": ["SET", 4, 4, "V"], "GUEST": ["GUEST", 0, 5, "V"], "GET": ["GET", 6, 0, "H"], "GUST": ["GUST", 4, 2, "H"], "SUE": ["SUE", 2, 3, "H"], "GUT": ["GUT", 4, 2, "V"], "TUG": ["TUG", 0, 3, "H"]}, "row": 7}, {"column": 8, "id": "2a259bb120261ba342abde4a5e246114", "coordinates": {"SUE": ["SUE", 1, 3, "H"], "SET": ["SET", 1, 3, "V"], "GUEST": ["GUEST", 2, 1, "V"], "GET": ["GET", 0, 5, "V"], "GUST": ["GUST", 3, 0, "H"], "USE": ["USE", 5, 0, "H"], "GUT": ["GUT", 0, 5, "H"], "TUG": ["TUG", 2, 5, "H"]}, "row": 7}, {"column": 8, "id": "d57554c8875ba23034a910f41fdebadd", "coordinates": {"USE": ["USE", 2, 3, "H"], "SET": ["SET", 4, 4, "V"], "GUEST": ["GUEST", 0, 5, "V"], "GET": ["GET", 6, 0, "H"], "GUST": ["GUST", 4, 2, "H"], "SUE": ["SUE", 3, 5, "H"], "GUT": ["GUT", 4, 2, "V"], "TUG": ["TUG", 6, 4, "H"]}, "row": 7}, {"column": 8, "id": "47b14da4cd3da348749ffa539654ee56", "coordinates": {"USE": ["USE", 4, 3, "V"], "SET": ["SET", 6, 2, "H"], "GUEST": ["GUEST", 4, 2, "H"], "GET": ["GET", 2, 5, "H"], "GUST": ["GUST", 2, 5, "V"], "SUE": ["SUE", 0, 6, "V"], "GUT": ["GUT", 2, 0, "H"], "TUG": ["TUG", 2, 2, "V"]}, "row": 7}, {"column": 8, "id": "378a65877656fa19b9664896e9eece3c", "coordinates": {"SUE": ["SUE", 0, 4, "V"], "SET": ["SET", 2, 5, "V"], "GUEST": ["GUEST", 2, 2, "H"], "GET": ["GET", 0, 6, "V"], "GUST": ["GUST", 2, 2, "V"], "USE": ["USE", 4, 6, "V"], "GUT": ["GUT", 5, 0, "H"], "TUG": ["TUG", 4, 5, "H"]}, "row": 7}, {"column": 9, "id": "7bcfcbd27800bae272f7073f10b03de5", "coordinates": {"SUE": ["SUE", 1, 6, "H"], "SET": ["SET", 1, 6, "V"], "GUEST": ["GUEST", 0, 2, "V"], "GET": ["GET", 4, 0, "H"], "GUST": ["GUST", 1, 1, "H"], "USE": ["USE", 2, 4, "H"], "GUT": ["GUT", 4, 0, "V"], "TUG": ["TUG", 1, 4, "V"]}, "row": 7}, {"column": 9, "id": "6edf34443729550000820f85ef4bdf88", "coordinates": {"SUE": ["SUE", 5, 0, "H"], "SET": ["SET", 3, 4, "H"], "GUEST": ["GUEST", 1, 4, "H"], "GET": ["GET", 4, 2, "V"], "GUST": ["GUST", 1, 4, "V"], "USE": ["USE", 0, 7, "V"], "GUT": ["GUT", 4, 2, "H"], "TUG": ["TUG", 3, 6, "V"]}, "row": 7}, {"column": 8, "id": "67362148c05a5ab1e6636a2e15881ff7", "coordinates": {"USE": ["USE", 6, 0, "H"], "SET": ["SET", 3, 3, "V"], "GUEST": ["GUEST", 4, 1, "H"], "GET": ["GET", 2, 5, "H"], "GUST": ["GUST", 4, 1, "V"], "SUE": ["SUE", 0, 6, "V"], "GUT": ["GUT", 2, 5, "V"], "TUG": ["TUG", 2, 7, "V"]}, "row": 8}, {"column": 8, "id": "51d882422eb2671b139710fae472b6d0", "coordinates": {"USE": ["USE", 1, 5, "H"], "SET": ["SET", 4, 5, "V"], "GUEST": ["GUEST", 2, 3, "V"], "GET": ["GET", 2, 3, "H"], "GUST": ["GUST", 6, 0, "H"], "SUE": ["SUE", 5, 3, "H"], "GUT": ["GUT", 0, 5, "V"], "TUG": ["TUG", 5, 1, "V"]}, "row": 8}, {"column": 9, "id": "d033f0653f68a92844c0d085ff532a62", "coordinates": {"USE": ["USE", 1, 4, "H"], "SET": ["SET", 5, 0, "H"], "GUEST": ["GUEST", 0, 4, "V"], "GET": ["GET", 0, 6, "V"], "GUST": ["GUST", 3, 2, "H"], "SUE": ["SUE", 5, 0, "V"], "GUT": ["GUT", 3, 2, "V"], "TUG": ["TUG", 2, 6, "H"]}, "row": 8}]}