{"letters": "ACLLLOY", "words": [{"pointNum": 1, "word": "LOCALLY", "def": "by a particular locality", "point": "12p."}, {"pointNum": 1, "word": "COLLY", "def": "make soiled, filthy, or dirty", "point": "10p."}, {"pointNum": 1, "word": "COALY", "def": "Resembling coal.", "point": "10p."}, {"pointNum": 8, "word": "ALLOY", "def": "a mixture containing two or more metallic elements or metallic and nonmetallic elements usually fused together or dissolving into each other when molten", "point": "8p."}, {"pointNum": 8, "word": "ALLYL", "def": "the univalent unsaturated organic radical C3H5", "point": "8p."}, {"pointNum": 8, "word": "LOLLY", "def": "informal terms for money", "point": "8p."}, {"pointNum": 8, "word": "LOYAL", "def": "steadfast in allegiance or duty", "point": "8p."}, {"pointNum": 7, "word": "LOCAL", "def": "public transport consisting of a bus or train that stops at all stations or stops", "point": "7p."}, {"pointNum": 9, "word": "ACYL", "def": "any group or radical of the form RCO- where R is an organic group", "point": "9p."}, {"pointNum": 9, "word": "CAYO", "def": "County/City (Proper noun)", "point": "9p."}, {"pointNum": 9, "word": "LACY", "def": "made of or resembling lace", "point": "9p."}, {"pointNum": 9, "word": "COLY", "def": "Any bird of either of the genera Colius or Urocolius, endemic to sub-Saharan Africa.", "point": "9p."}, {"pointNum": 9, "word": "CLAY", "def": "a very fine-grained soil that is plastic when moist but hard when fired", "point": "9p."}, {"pointNum": 9, "word": "CLOY", "def": "supply or feed to surfeit", "point": "9p."}, {"pointNum": 7, "word": "YOLA", "def": "City in Nigeria (Proper noun)", "point": "7p."}, {"pointNum": 7, "word": "ALLY", "def": "a friendly nation", "point": "7p."}, {"pointNum": 6, "word": "LOCA", "def": "", "point": "6p."}, {"pointNum": 6, "word": "COLA", "def": "large genus of African trees bearing kola nuts", "point": "6p."}, {"pointNum": 6, "word": "COAL", "def": "fossil fuel consisting of carbonized vegetable matter deposited in the Carboniferous period", "point": "6p."}, {"pointNum": 6, "word": "CALO", "def": "", "point": "6p."}, {"pointNum": 6, "word": "CALL", "def": "a telephone connection", "point": "6p."}, {"pointNum": 4, "word": "LALL", "def": "", "point": "4p."}, {"pointNum": 4, "word": "LOLA", "def": "County/City (Proper noun)", "point": "4p."}, {"pointNum": 4, "word": "OLLA", "def": "leaf or strip from a leaf of the talipot palm used in India for writing paper", "point": "4p."}, {"pointNum": 4, "word": "LOLL", "def": "hang loosely or laxly", "point": "4p."}, {"pointNum": 8, "word": "CAY", "def": "a coral reef off the southern coast of Florida", "point": "8p."}, {"pointNum": 8, "word": "COY", "def": "affectedly modest or shy especially in a playful or provocative way", "point": "8p."}, {"pointNum": 6, "word": "LAY", "def": "a narrative song with a recurrent refrain", "point": "6p."}, {"pointNum": 5, "word": "OCA", "def": "South American wood sorrel cultivated for its edible tubers", "point": "5p."}, {"pointNum": 5, "word": "LAC", "def": "resinlike substance secreted by certain lac insects", "point": "5p."}, {"pointNum": 5, "word": "COL", "def": "a pass between mountain peaks", "point": "5p."}, {"pointNum": 3, "word": "ALL", "def": "quantifier", "point": "3p."}, {"pointNum": 5, "word": "AY", "def": "academic year .", "point": "5p."}, {"pointNum": 5, "word": "YO", "def": "", "point": "5p."}, {"pointNum": 5, "word": "YA", "def": "yea; yes.", "point": "5p."}, {"pointNum": 5, "word": "OY", "def": "", "point": "5p."}, {"pointNum": 2, "word": "LO", "def": "", "point": "2p."}, {"pointNum": 2, "word": "LA", "def": "a white soft metallic element that tarnishes readily", "point": "2p."}, {"pointNum": 2, "word": "AL", "def": "The Indian mulberry , , especially as used to make dye.", "point": "2p."}]}