{"letters": "CEIMR", "words": [{"pointNum": 9, "word": "CRIME", "def": "(criminal law) an act punishable by law", "point": "9p."}, {"pointNum": 8, "word": "MICE", "def": "any of numerous small rodents typically resembling diminutive rats having pointed snouts and small ears on elongated bodies with slender usually hairless tails", "point": "8p."}, {"pointNum": 8, "word": "MERC", "def": "A mercenary.", "point": "8p."}, {"pointNum": 8, "word": "EMIC", "def": "Of or pertaining to the analysis of a cultural system or its features from the perspective of a participant in that culture.", "point": "8p."}, {"pointNum": 6, "word": "RIME", "def": "ice crystals forming a white deposit (especially on objects outside)", "point": "6p."}, {"pointNum": 6, "word": "RICE", "def": "grains used as food either unpolished or more often polished", "point": "6p."}, {"pointNum": 6, "word": "MIRE", "def": "a soft wet area of low-lying land that sinks underfoot", "point": "6p."}, {"pointNum": 6, "word": "EMIR", "def": "an independent ruler or chieftain (especially in Africa or Arabia)", "point": "6p."}, {"pointNum": 6, "word": "CIRE", "def": "", "point": "6p."}, {"pointNum": 7, "word": "MIC", "def": "Microphone.", "point": "7p."}, {"pointNum": 5, "word": "MIE", "def": "County/City (Proper noun)", "point": "5p."}, {"pointNum": 5, "word": "REM", "def": "a recurring sleep state during which dreaming occurs", "point": "5p."}, {"pointNum": 5, "word": "RIM", "def": "the shape of a raised edge of a more or less circular object", "point": "5p."}, {"pointNum": 5, "word": "REC", "def": "A recommendation or suggestion.", "point": "5p."}, {"pointNum": 5, "word": "MIR", "def": "A Russian village community.", "point": "5p."}, {"pointNum": 5, "word": "ICE", "def": "water frozen in the solid state", "point": "5p."}, {"pointNum": 3, "word": "REI", "def": "An old Portuguese money of account .", "point": "3p."}, {"pointNum": 3, "word": "IRE", "def": "a strong emotion", "point": "3p."}, {"pointNum": 4, "word": "MI", "def": "destruction of heart tissue resulting from obstruction of the blood supply to the heart muscle", "point": "4p."}, {"pointNum": 4, "word": "ME", "def": "a state in New England", "point": "4p."}, {"pointNum": 4, "word": "EM", "def": "a quad with a square body", "point": "4p."}, {"pointNum": 2, "word": "ER", "def": "a trivalent metallic element of the rare earth group", "point": "2p."}, {"pointNum": 2, "word": "RE", "def": "a rare heavy polyvalent metallic element that resembles manganese chemically and is used in some alloys", "point": "2p."}]}