{"letters": "DDEEIN", "words": [{"pointNum": 8, "word": "INDEED", "def": "in truth (often tends to intensify)", "point": "8p."}, {"pointNum": 8, "word": "DENIED", "def": "declare untrue", "point": "8p."}, {"pointNum": 7, "word": "NIDED", "def": "", "point": "7p."}, {"pointNum": 7, "word": "ENDED", "def": "having come or been brought to a conclusion", "point": "7p."}, {"pointNum": 7, "word": "DINED", "def": "", "point": "7p."}, {"pointNum": 6, "word": "DIENE", "def": "An organic compound, especially a hydrocarbon, containing two double bond s.", "point": "6p."}, {"pointNum": 6, "word": "DIED", "def": "", "point": "6p."}, {"pointNum": 6, "word": "DEED", "def": "a legal document signed and sealed and delivered to effect a transfer of property and to show the legal right to possess it", "point": "6p."}, {"pointNum": 5, "word": "ENID", "def": "City in United States of America (Proper noun)", "point": "5p."}, {"pointNum": 5, "word": "ENDE", "def": "City in Indonesia (Proper noun)", "point": "5p."}, {"pointNum": 5, "word": "NIDE", "def": "A nest of pheasants.", "point": "5p."}, {"pointNum": 5, "word": "NEED", "def": "a condition requiring relief", "point": "5p."}, {"pointNum": 5, "word": "EIDE", "def": "", "point": "5p."}, {"pointNum": 5, "word": "DINE", "def": "have supper", "point": "5p."}, {"pointNum": 5, "word": "DENE", "def": "A member of the Athabascan peoples.", "point": "5p."}, {"pointNum": 5, "word": "DENI", "def": "A subdivision of currency, equal to 0. 01 Macedonian denar.", "point": "5p."}, {"pointNum": 5, "word": "DID", "def": "engage in", "point": "5p."}, {"pointNum": 4, "word": "END", "def": "either extremity of something that has length", "point": "4p."}, {"pointNum": 4, "word": "DIN", "def": "a loud harsh or strident noise", "point": "4p."}, {"pointNum": 4, "word": "DIE", "def": "a small cube with 1 to 6 spots on the six faces", "point": "4p."}, {"pointNum": 4, "word": "DEN", "def": "the habitation of wild animals", "point": "4p."}, {"pointNum": 4, "word": "DEE", "def": "Something shaped like the letter D, such as a dee lock .", "point": "4p."}, {"pointNum": 3, "word": "NEE", "def": "(meaning literally `born') used to indicate the maiden or family name of a married woman", "point": "3p."}, {"pointNum": 3, "word": "ED", "def": "", "point": "3p."}, {"pointNum": 3, "word": "ID", "def": "a state in the Rocky Mountains", "point": "3p."}, {"pointNum": 3, "word": "DE", "def": "a Mid-Atlantic state", "point": "3p."}, {"pointNum": 2, "word": "NE", "def": "Not.", "point": "2p."}, {"pointNum": 2, "word": "IN", "def": "a unit of length equal to one twelfth of a foot", "point": "2p."}, {"pointNum": 2, "word": "EN", "def": "half the width of an em", "point": "2p."}]}