{"letters": "DDLOY", "words": [{"pointNum": 1, "word": "ODDLY", "def": "in a manner differing from the usual or expected", "point": "10p."}, {"pointNum": 8, "word": "OLDY", "def": "", "point": "8p."}, {"pointNum": 8, "word": "ODYL", "def": "od.", "point": "8p."}, {"pointNum": 7, "word": "YOD", "def": "A palatal approximant.", "point": "7p."}, {"pointNum": 5, "word": "ODD", "def": "not divisible by two", "point": "5p."}, {"pointNum": 4, "word": "DOL", "def": "a unit of pain intensity", "point": "4p."}, {"pointNum": 4, "word": "OLD", "def": "past times (especially in the phrase `in days of old')", "point": "4p."}, {"pointNum": 5, "word": "OY", "def": "", "point": "5p."}, {"pointNum": 5, "word": "YO", "def": "", "point": "5p."}, {"pointNum": 3, "word": "DO", "def": "an uproarious party", "point": "3p."}, {"pointNum": 3, "word": "OD", "def": "a doctor's degree in optometry", "point": "3p."}, {"pointNum": 2, "word": "LO", "def": "", "point": "2p."}]}