{"letters": "DLOT", "words": [{"pointNum": 5, "word": "DOLT", "def": "a person who is not very bright", "point": "5p."}, {"pointNum": 5, "word": "TOLD", "def": "express in words", "point": "5p."}, {"pointNum": 4, "word": "DOL", "def": "a unit of pain intensity", "point": "4p."}, {"pointNum": 4, "word": "DOT", "def": "a very small circular shape", "point": "4p."}, {"pointNum": 4, "word": "OLD", "def": "past times (especially in the phrase `in days of old')", "point": "4p."}, {"pointNum": 4, "word": "TOD", "def": "a unit of weight for wool equal to about 28 pounds", "point": "4p."}, {"pointNum": 3, "word": "LOT", "def": "(often followed by `of') a large number or amount or extent", "point": "3p."}, {"pointNum": 3, "word": "OLT", "def": "County/City (Proper noun)", "point": "3p."}, {"pointNum": 3, "word": "DO", "def": "an uproarious party", "point": "3p."}, {"pointNum": 3, "word": "OD", "def": "a doctor's degree in optometry", "point": "3p."}, {"pointNum": 2, "word": "LO", "def": "", "point": "2p."}, {"pointNum": 2, "word": "TO", "def": "Toward a closed, touching or engaging position.", "point": "2p."}]}