{"letters": "GINPRS", "words": [{"pointNum": 9, "word": "SPRING", "def": "the season of growth", "point": "9p."}, {"pointNum": 8, "word": "SPRIG", "def": "a small branch or division of a branch (especially a terminal division)", "point": "8p."}, {"pointNum": 8, "word": "PRIGS", "def": "a person regarded as arrogant and annoying", "point": "8p."}, {"pointNum": 8, "word": "PINGS", "def": "a river in western Thailand", "point": "8p."}, {"pointNum": 8, "word": "GRIPS", "def": "the act of grasping", "point": "8p."}, {"pointNum": 7, "word": "PIRNS", "def": "Plural of pirn.", "point": "7p."}, {"pointNum": 6, "word": "GRINS", "def": "a facial expression characterized by turning up the corners of the mouth", "point": "6p."}, {"pointNum": 6, "word": "GIRNS", "def": "", "point": "6p."}, {"pointNum": 6, "word": "RINGS", "def": "gymnastic apparatus consisting of a pair of heavy metal circles (usually covered with leather) suspended by ropes", "point": "6p."}, {"pointNum": 7, "word": "PRIG", "def": "a person regarded as arrogant and annoying", "point": "7p."}, {"pointNum": 7, "word": "PIGS", "def": "domestic swine", "point": "7p."}, {"pointNum": 7, "word": "PING", "def": "a river in western Thailand", "point": "7p."}, {"pointNum": 7, "word": "GIPS", "def": "deprive of by deceit", "point": "7p."}, {"pointNum": 7, "word": "GRIP", "def": "the act of grasping", "point": "7p."}, {"pointNum": 6, "word": "SPIN", "def": "a swift whirling motion (usually of a missile)", "point": "6p."}, {"pointNum": 6, "word": "NIPS", "def": "a small drink of liquor", "point": "6p."}, {"pointNum": 6, "word": "RIPS", "def": "a dissolute man in fashionable society", "point": "6p."}, {"pointNum": 6, "word": "PIRN", "def": "A cone shaped spool or bobbin on which thread or yarn is wound used most often for weaving.", "point": "6p."}, {"pointNum": 6, "word": "PINS", "def": "a piece of jewelry that is pinned onto the wearer's garment", "point": "6p."}, {"pointNum": 6, "word": "SNIP", "def": "a small piece of anything (especially a piece that has been snipped off)", "point": "6p."}, {"pointNum": 5, "word": "SING", "def": "deliver by singing", "point": "5p."}, {"pointNum": 5, "word": "SIGN", "def": "a perceptible indication of something not immediately apparent (as a visible clue that something has happened)", "point": "5p."}, {"pointNum": 5, "word": "RING", "def": "a characteristic sound", "point": "5p."}, {"pointNum": 5, "word": "RIGS", "def": "gear (including necessary machinery) for a particular enterprise", "point": "5p."}, {"pointNum": 5, "word": "GRIN", "def": "a facial expression characterized by turning up the corners of the mouth", "point": "5p."}, {"pointNum": 5, "word": "GIRN", "def": "To grimace; to snarl.", "point": "5p."}, {"pointNum": 5, "word": "GINS", "def": "strong liquor flavored with juniper berries", "point": "5p."}, {"pointNum": 4, "word": "RINS", "def": "", "point": "4p."}, {"pointNum": 6, "word": "PIG", "def": "domestic swine", "point": "6p."}, {"pointNum": 6, "word": "GIP", "def": "deprive of by deceit", "point": "6p."}, {"pointNum": 5, "word": "RIP", "def": "a dissolute man in fashionable society", "point": "5p."}, {"pointNum": 5, "word": "NIP", "def": "a small drink of liquor", "point": "5p."}, {"pointNum": 5, "word": "PIN", "def": "a piece of jewelry that is pinned onto the wearer's garment", "point": "5p."}, {"pointNum": 5, "word": "SIP", "def": "a small drink", "point": "5p."}, {"pointNum": 5, "word": "PIS", "def": "the ratio of the circumference to the diameter of a circle", "point": "5p."}, {"pointNum": 5, "word": "PSI", "def": "a unit of pressure", "point": "5p."}, {"pointNum": 4, "word": "GIN", "def": "strong liquor flavored with juniper berries", "point": "4p."}, {"pointNum": 4, "word": "RIG", "def": "gear (including necessary machinery) for a particular enterprise", "point": "4p."}, {"pointNum": 3, "word": "RIN", "def": "", "point": "3p."}, {"pointNum": 3, "word": "SIN", "def": "estrangement from god", "point": "3p."}, {"pointNum": 3, "word": "SIR", "def": "term of address for a man", "point": "3p."}, {"pointNum": 3, "word": "SRI", "def": "", "point": "3p."}, {"pointNum": 3, "word": "INS", "def": "an agency in the Department of Justice that enforces laws and regulations for the admission of foreign-born persons to the United States", "point": "3p."}, {"pointNum": 3, "word": "NIS", "def": "City in Serbia (Proper noun)", "point": "3p."}, {"pointNum": 4, "word": "PI", "def": "the ratio of the circumference to the diameter of a circle", "point": "4p."}, {"pointNum": 3, "word": "IG", "def": "County/City (Proper noun)", "point": "3p."}, {"pointNum": 2, "word": "IS", "def": "a nonmetallic element belonging to the halogens", "point": "2p."}, {"pointNum": 2, "word": "SI", "def": "a tetravalent nonmetallic element", "point": "2p."}, {"pointNum": 2, "word": "IN", "def": "a unit of length equal to one twelfth of a foot", "point": "2p."}]}