{"letters": "ILLOPW", "words": [{"pointNum": 1, "word": "PILLOW", "def": "a cushion to support the head of a sleeping person", "point": "11p."}, {"pointNum": 9, "word": "PLOW", "def": "a farm tool having one or more heavy blades to break the soil and cut a furrow prior to sowing", "point": "9p."}, {"pointNum": 7, "word": "WILL", "def": "the capability of conscious choice and decision and intention", "point": "7p."}, {"pointNum": 6, "word": "POLL", "def": "an inquiry into public opinion conducted by interviewing a random sample of people", "point": "6p."}, {"pointNum": 6, "word": "PILL", "def": "something that resembles a tablet of medicine in shape or size", "point": "6p."}, {"pointNum": 4, "word": "LILO", "def": "An inflatable air mattress.", "point": "4p."}, {"pointNum": 8, "word": "WOP", "def": "(ethnic slur) offensive term for a person of Italian descent", "point": "8p."}, {"pointNum": 8, "word": "POW", "def": "a person who surrenders to (or is taken by) the enemy in time of war", "point": "8p."}, {"pointNum": 6, "word": "LOW", "def": "an air mass of lower pressure", "point": "6p."}, {"pointNum": 6, "word": "IWO", "def": "City in Nigeria (Proper noun)", "point": "6p."}, {"pointNum": 6, "word": "OWL", "def": "nocturnal bird of prey with hawk-like beak and claws and large head with front-facing eyes", "point": "6p."}, {"pointNum": 5, "word": "LOP", "def": "cut off from a whole", "point": "5p."}, {"pointNum": 5, "word": "LIP", "def": "either of two fleshy folds of tissue that surround the mouth and play a role in speaking", "point": "5p."}, {"pointNum": 5, "word": "POI", "def": "Hawaiian dish of taro root pounded to a paste and often allowed to ferment", "point": "5p."}, {"pointNum": 5, "word": "POL", "def": "a person active in party politics", "point": "5p."}, {"pointNum": 3, "word": "OIL", "def": "a slippery or viscous liquid or liquefiable substance not miscible with water", "point": "3p."}, {"pointNum": 3, "word": "ILL", "def": "an often persistent bodily disorder or disease", "point": "3p."}, {"pointNum": 3, "word": "ILO", "def": "City in Peru (Proper noun)", "point": "3p."}, {"pointNum": 5, "word": "WO", "def": "", "point": "5p."}, {"pointNum": 5, "word": "OW", "def": "", "point": "5p."}, {"pointNum": 4, "word": "PO", "def": "City in Burkina Faso (Proper noun)", "point": "4p."}, {"pointNum": 4, "word": "PI", "def": "the ratio of the circumference to the diameter of a circle", "point": "4p."}, {"pointNum": 4, "word": "OP", "def": "op Op art ; a style of abstract art.", "point": "4p."}, {"pointNum": 2, "word": "LO", "def": "", "point": "2p."}, {"pointNum": 2, "word": "OI", "def": "A working-class punk rock  subgenre of the 1970s, sometimes associated with racism.", "point": "2p."}, {"pointNum": 2, "word": "LI", "def": "a soft silver-white univalent element of the alkali metal group", "point": "2p."}]}