{"letters": "ILMMSU", "words": [{"pointNum": 8, "word": "MUMS", "def": "of China", "point": "8p."}, {"pointNum": 6, "word": "SLIM", "def": "take off weight", "point": "6p."}, {"pointNum": 6, "word": "MILS", "def": "a Cypriot monetary unit equal to one thousandth of a pound", "point": "6p."}, {"pointNum": 6, "word": "LUMS", "def": "Plural of lum.", "point": "6p."}, {"pointNum": 6, "word": "SLUM", "def": "a district of a city marked by poverty and inferior living conditions", "point": "6p."}, {"pointNum": 7, "word": "MIM", "def": "", "point": "7p."}, {"pointNum": 7, "word": "MUM", "def": "of China", "point": "7p."}, {"pointNum": 7, "word": "UMM", "def": "", "point": "7p."}, {"pointNum": 5, "word": "ISM", "def": "a belief (or system of beliefs) accepted as authoritative by some group or school", "point": "5p."}, {"pointNum": 5, "word": "MUS", "def": "type genus of the Muridae: common house mice", "point": "5p."}, {"pointNum": 5, "word": "ULM", "def": "City in Germany (Proper noun)", "point": "5p."}, {"pointNum": 5, "word": "SUM", "def": "a quantity of money", "point": "5p."}, {"pointNum": 5, "word": "SIM", "def": "A simulation.", "point": "5p."}, {"pointNum": 5, "word": "MIS", "def": "destruction of heart tissue resulting from obstruction of the blood supply to the heart muscle", "point": "5p."}, {"pointNum": 5, "word": "MIL", "def": "a Cypriot monetary unit equal to one thousandth of a pound", "point": "5p."}, {"pointNum": 5, "word": "LUM", "def": "A chimney.", "point": "5p."}, {"pointNum": 3, "word": "LIS", "def": "a soft silver-white univalent element of the alkali metal group", "point": "3p."}, {"pointNum": 6, "word": "MM", "def": "Education Master of Music.", "point": "6p."}, {"pointNum": 4, "word": "UM", "def": "Alternative spelling of \u00b5m.", "point": "4p."}, {"pointNum": 4, "word": "MU", "def": "the 12th letter of the Greek alphabet", "point": "4p."}, {"pointNum": 4, "word": "MI", "def": "destruction of heart tissue resulting from obstruction of the blood supply to the heart muscle", "point": "4p."}, {"pointNum": 2, "word": "US", "def": "North American republic containing 50 states - 48 conterminous states in North America plus Alaska in northwest North America and the Hawaiian Islands in the Pacific Ocean", "point": "2p."}, {"pointNum": 2, "word": "LI", "def": "a soft silver-white univalent element of the alkali metal group", "point": "2p."}, {"pointNum": 2, "word": "SI", "def": "a tetravalent nonmetallic element", "point": "2p."}, {"pointNum": 2, "word": "IS", "def": "a nonmetallic element belonging to the halogens", "point": "2p."}]}